deutschland/klinikatlas/__init__.py
deutschland/klinikatlas/api/__init__.py
deutschland/klinikatlas/api/default_api.py
deutschland/klinikatlas/api_client.py
deutschland/klinikatlas/apis/__init__.py
deutschland/klinikatlas/configuration.py
deutschland/klinikatlas/exceptions.py
deutschland/klinikatlas/model/__init__.py
deutschland/klinikatlas/model/fileadmin_json_german_places_json_get200_response_inner.py
deutschland/klinikatlas/model/fileadmin_json_german_states_json_get200_response_inner.py
deutschland/klinikatlas/model/fileadmin_json_icd_codes_json_get200_response_inner.py
deutschland/klinikatlas/model/fileadmin_json_locations_json_get200_response_inner.py
deutschland/klinikatlas/model/fileadmin_json_ops_codes_json_get200_response_inner.py
deutschland/klinikatlas/model/fileadmin_json_states_json_get200_response_inner.py
deutschland/klinikatlas/model/searchresults_get200_response.py
deutschland/klinikatlas/model/searchresults_get200_response_filters.py
deutschland/klinikatlas/model/searchresults_get200_response_filters_fields_inner.py
deutschland/klinikatlas/model/searchresults_get200_response_filters_fields_inner_options_inner.py
deutschland/klinikatlas/model/searchresults_get200_response_filters_fields_inner_slider_options_inner.py
deutschland/klinikatlas/model/searchresults_get200_response_meta_infos.py
deutschland/klinikatlas/model/searchresults_get200_response_meta_infos_search_arguments.py
deutschland/klinikatlas/model/searchresults_get200_response_results_inner.py
deutschland/klinikatlas/model/searchresults_get200_response_results_inner_content.py
deutschland/klinikatlas/model/searchresults_get200_response_results_inner_content_items_inner.py
deutschland/klinikatlas/model/searchresults_get200_response_sortings.py
deutschland/klinikatlas/model/searchresults_get200_response_sortings_fields_inner.py
deutschland/klinikatlas/model/searchresults_get200_response_sortings_fields_inner_options_inner.py
deutschland/klinikatlas/model_utils.py
de_klinikatlas-1.0.0.dist-info/METADATA
de_klinikatlas-1.0.0.dist-info/WHEEL
de_klinikatlas-1.0.0.dist-info/RECORD
